{
  "title": "MesseMap",
  "orientation": "Orientaci칩n",
  "vertical": "Vertical",
  "horizontal": "Horizontal",
  "action": {
    "close": "Cerca"
  },
  "style": {
    "title": "Estilo",
    "mapStyle": "Dise침o del mapa",
    "darkTheme": "Tema oscuro",
    "upText": "Poner texto encima",
    "std": "Est치ndar",
    "travel": "Viaje",
    "frame": "Marco",
    "pure": "Puro",
    "pantone": "Pantone",
    "map": "Mapa",
    "window": "Ventana",
    "air": "Air",
    "hipster": "Hipster"
  },
  "text": {
    "title": "Textos",
    "mapTitle": "T칤tulo",
    "mapTitlePlaceholder": "T칤tulo del mapa",
    "mapSubtitle": "Subt칤tulos",
    "mapSubtitlePlaceholder": "Subt칤tulo del mapa",
    "mapComment": "Comentario",
    "mapCommentPlaceholder": "Comentar sobre el mapa"
  },
  "export": {
    "title": "Par치metro de exportaci칩n",
    "dimension": "Dimensiones",
    "at": "a",
    "format": "Formato de archivo",
    "button": "Exportar",
    "credits": "Cr칠ditos"
  },
  "download": {
    "title": "Tu cartel est치 siendo preparado.",
    "subtitle": "Espere mientras la aplicaci칩n recopila todos los datos requeridos",
    "stylePrep": "Preparando el estilo del mapa para la exportaci칩n...",
    "tileLoad": "Esperando a que se carguen todos los mosaicos del mapa...",
    "printStart": "Teselas cargadas, exportaci칩n iniciada...",
    "outputFile": "Crear archivo de salida...",
    "saveToDisk": "Exportaci칩n realizada. Actualmente guardando la imagen en el disco...",
    "restoreMap": "Restaurar el estado inicial del mapa..."
  },
  "search": {
    "placeholder": "Buscar...",
    "cancel": "Cancelar",
    "error": "Sin resultados..."
  },
  "theme": {
    "title": "Modificaci칩n de tema",
    "lightTheme": "Tema ligero",
    "darkTheme": "Tema oscuro",
    "bg": "Fondo",
    "txt": "Texto",
    "txtAlt": "Texto alternativo",
    "default": "Restaurar a los valores predeterminados"
  },
  "credit": {
    "line1": "Una aplicaci칩n propuesta por <a href=\"https://messe-basse-production.com\" target=\"_blank\" rel=\"noopener noreferer\">Messe Basse Production</a>. Sin cookies, sin rastreadores, est치s navegando de forma segura aqu칤.",
    "line2": "Los mapas son amablemente elaborados por <a href=\"https://www.openstreetmap.fr/\" target=\"_blank\" rel=\"noopener noreferer\">OpenStreetMap</a>, <a href=\"https:// www.geoportail.gouv.fr/\" target=\"_blank\" rel=\"noopener noreferer\">GeoPortail</a>, <a href=\"https://www.esri.com/\" target=\"_blank\" rel=\"noopener noreferer\">ESRI</a>, <a href=\"http://stamen.com\" target=\"_blank\" rel=\"noopener noreferer \">Dise침o de estambre</a>, <a href=\"https://carto.com/attributions\" target=\"_blank\" rel=\"noopener noreferer\">Carto</a> y <a href=\"https://www.mapiful.com/\" target=\"_blank\" rel=\"noopener noreferer\">Mapiful</a>, publicado en <a href=\"http:/ /www.openstreetmap.org/copyright\" target=\"_blank\" rel=\"noopener noreferer\">ODbL</a> licencia. Estamos muy agradecidos con esos proveedores.",
    "line3": "Datos de mapas cortes칤a de ESRI, i-cubed, Mapiful, USDA, USGS, AEX, GeoEye, Getmapping, Aerogrid, IGN, IGP, UPR-EGP, OpenStreetMap, Carto, Stamen Design y GIS User Community.",
    "line4": "MesseMap tiene una licencia de c칩digo abierto GPL-3.0 y se basa en las bibliotecas <a href=\"https://leafletjs.com/\" target=\"_blank\" rel=\"noopener noreferer\">Folleto</a>, <a href=\"https://github. com/mutsuyuki/Leaflet.SmoothWheelZoom\" target=\"_blank\" rel=\"noopener noreferer\">Leaflet.SmoothWheelZoom</a>, <a href=\"https://github.com/stefanocudini/leaflet -buscar\" target=\"_blank\" rel=\"noopener noreferer\">b칰squeda de prospectos</a> <a href=\"https://html2canvas.hertzen.com/\" target=\"_blank \" rel=\"noopener noreferer\">html2canvas</a> y <a href=\"https://github.com/parallax/jsPDF/\" target=\"_blank\" rel=\"noopener noreferer \">jsPDF</a>. El c칩digo fuente de esta aplicaci칩n est치 disponible en <a href=\"https://github.com/MesseBasseProduction/MesseMap/\" target=\"_blank\" rel=\"noopener noreferer\">GitHub</a > repositorio. Cualquier aporte es bienvenido!",
    "lang": "Lenguaje de interfaz",
    "fr": "游游 Franc칠s",
    "en": "游섫릖 Ingl칠s",
    "es": "游쀯릖 Espa침ol",
    "de": "游뾇릖 Alem치n",
    "it": "游쉻릖 Italiano",
    "pt": "游왫릖 Portugu칠s"
  }
}
